[
  {
    "id": "1",
    "title": "The Lost City of Stars",
    "oldPrice": 499,
    "price": 399,
    "image": "https://fakestoreapi.com/img/51Y5NI-I5jL._AC_UX679_.jpg",
    "carouselImages": [
      "https://fakestoreapi.com/img/51Y5NI-I5jL._AC_UX679_.jpg"
    ],
    "color": "Default",
    "size": "Paperback"
  },
  {
    "id": "2",
    "title": "Secrets of the Deep Sea",
    "oldPrice": 349,
    "price": 299,
    "image": "https://fakestoreapi.com/img/71li-ujtlUL._AC_UX679_.jpg",
    "carouselImages": [
      "https://fakestoreapi.com/img/71li-ujtlUL._AC_UX679_.jpg"
    ],
    "color": "Default",
    "size": "Paperback"
  },
  {
    "id": "3",
    "title": "Love in the Monsoon",
    "oldPrice": 299,
    "price": 249,
    "image": "https://fakestoreapi.com/img/61IBBVJvSDL._AC_SY879_.jpg",
    "carouselImages": [
      "https://fakestoreapi.com/img/61IBBVJvSDL._AC_SY879_.jpg"
    ],
    "color": "Default",
    "size": "Paperback"
  },
  {
    "id": "4",
    "title": "The Code Breakers",
    "oldPrice": 549,
    "price": 449,
    "image": "https://fakestoreapi.com/img/81QpkIctqPL._AC_SX679_.jpg",
    "carouselImages": [
      "https://fakestoreapi.com/img/81QpkIctqPL._AC_SX679_.jpg"
    ],
    "color": "Default",
    "size": "Paperback"
  },
  {
    "id": "5",
    "title": "Mastering JavaScript",
    "oldPrice": 699,
    "price": 599,
    "image": "https://fakestoreapi.com/img/71HblAHs5xL._AC_SY879_.jpg",
    "carouselImages": [
      "https://fakestoreapi.com/img/71HblAHs5xL._AC_SY879_.jpg"
    ],
    "color": "Default",
    "size": "Paperback"
  },
  {
    "id": "6",
    "title": "The Quantum Paradox",
    "oldPrice": 599,
    "price": 499,
    "image": "https://fakestoreapi.com/img/61mtL5D5cL._AC_SX679_.jpg",
    "carouselImages": [
      "https://fakestoreapi.com/img/61mtL5D5cL._AC_SX679_.jpg"
    ],
    "color": "Default",
    "size": "Hardcover"
  },
  {
    "id": "7",
    "title": "Ancient Civilizations",
    "oldPrice": 449,
    "price": 379,
    "image": "https://fakestoreapi.com/img/71pWzhdJNwL._AC_UL640_QL65_ML3_.jpg",
    "carouselImages": [
      "https://fakestoreapi.com/img/71pWzhdJNwL._AC_UL640_QL65_ML3_.jpg"
    ],
    "color": "Default",
    "size": "Paperback"
  },
  {
    "id": "8",
    "title": "Culinary Arts Masterclass",
    "oldPrice": 799,
    "price": 649,
    "image": "https://fakestoreapi.com/img/61sbMiUnoGL._AC_UL640_QL65_ML3_.jpg",
    "carouselImages": [
      "https://fakestoreapi.com/img/61sbMiUnoGL._AC_UL640_QL65_ML3_.jpg"
    ],
    "color": "Default",
    "size": "Hardcover"
  },
  {
    "id": "9",
    "title": "The Art of Mindfulness",
    "oldPrice": 399,
    "price": 329,
    "image": "https://fakestoreapi.com/img/71YAIFU48IL._AC_UL640_QL65_ML3_.jpg",
    "carouselImages": [
      "https://fakestoreapi.com/img/71YAIFU48IL._AC_UL640_QL65_ML3_.jpg"
    ],
    "color": "Default",
    "size": "Paperback"
  },
  {
    "id": "10",
    "title": "Space Exploration: A History",
    "oldPrice": 699,
    "price": 559,
    "image": "https://fakestoreapi.com/img/51UDEzMJVpL._AC_UL640_QL65_ML3_.jpg",
    "carouselImages": [
      "https://fakestoreapi.com/img/51UDEzMJVpL._AC_UL640_QL65_ML3_.jpg"
    ],
    "color": "Default",
    "size": "Hardcover"
  },
  {
    "id": "11",
    "title": "Python Programming Essentials",
    "oldPrice": 649,
    "price": 549,
    "image": "https://fakestoreapi.com/img/61IBBVJvSDL._AC_SY879_.jpg",
    "carouselImages": [
      "https://fakestoreapi.com/img/61IBBVJvSDL._AC_SY879_.jpg"
    ],
    "color": "Default",
    "size": "Paperback"
  },
  {
    "id": "12",
    "title": "Mysteries of the Rainforest",
    "oldPrice": 379,
    "price": 299,
    "image": "https://fakestoreapi.com/img/71kWymZ+c+L._AC_UL640_QL65_ML3_.jpg",
    "carouselImages": [
      "https://fakestoreapi.com/img/71kWymZ+c+L._AC_UL640_QL65_ML3_.jpg"
    ],
    "color": "Default",
    "size": "Paperback"
  },
  {
    "id": "13",
    "title": "Financial Freedom Guide",
    "oldPrice": 529,
    "price": 429,
    "image": "https://fakestoreapi.com/img/61mtL5D5cL._AC_SX679_.jpg",
    "carouselImages": [
      "https://fakestoreapi.com/img/61mtL5D5cL._AC_SX679_.jpg"
    ],
    "color": "Default",
    "size": "Paperback"
  },
  {
    "id": "14",
    "title": "Modern Architecture Design",
    "oldPrice": 899,
    "price": 749,
    "image": "https://fakestoreapi.com/img/71li-ujtlUL._AC_UX679_.jpg",
    "carouselImages": [
      "https://fakestoreapi.com/img/71li-ujtlUL._AC_UX679_.jpg"
    ],
    "color": "Default",
    "size": "Hardcover"
  },
  {
    "id": "15",
    "title": "The Psychology of Success",
    "oldPrice": 479,
    "price": 399,
    "image": "https://fakestoreapi.com/img/81QpkIctqPL._AC_SX679_.jpg",
    "carouselImages": [
      "https://fakestoreapi.com/img/81QpkIctqPL._AC_SX679_.jpg"
    ],
    "color": "Default",
    "size": "Paperback"
  }
]
